{
  "fees": {
    "effective_bps": 0.0,
    "per_symbol_bps": {}
  },
  "intraday_caps": {
    "drawdown_proxy_pct": 0.0
  },
  "position_skew": {
    "positions": {}
  },
  "runtime": {
    "utc": "1970-01-01T00:00:00Z",
    "version": "0.1.0",
    "git_sha": "unknown",
    "mode": "sim",
    "env": "dev"
  },
  "pnl": {
    "total_net_bps": 0.0,
    "total_taker_share_pct": 0.0,
    "total_order_age_p95_ms": 0.0,
    "net_bps": {},
    "taker_share_pct": {},
    "order_age_p95_ms": {}
  },
  "turnover": {
    "usd": {},
    "total_usd": 0.0
  },
  "latency": {
    "p95_ms": {},
    "replace_rate_per_min": {},
    "cancel_batch_events_total": {}
  },
  "edge": {
    "gross_bps": {},
    "fees_bps": {},
    "adverse_bps": {},
    "slippage_bps": {},
    "inventory_bps": {}
  }
}


